visual/__init__.py
visual/utils.py
visual/core/__init__.py
visual/core/io.py
visual/core/watcher.py
visual/types/graph.py
visual/types/pointable.py
visual/types/snapshot.py
visual/types/watchable/__init__.py
visual/types/watchable/base.py
visual/types/watchable/var.py
visual/types/watchable/ds/__init__.py
visual/types/watchable/ds/array.py
visual/types/watchable/ds/array2d.py
visual/types/watchable/ds/array3d.py
visual/types/watchable/ds/arraynd.py
visual/types/watchable/ds/nodes.py
visual/types/watchable/ds/ext/.gitkeep
algo_visualizer-0.0.2.dist-info/METADATA
algo_visualizer-0.0.2.dist-info/WHEEL
algo_visualizer-0.0.2.dist-info/licenses/LICENSE
algo_visualizer-0.0.2.dist-info/RECORD
