Metadata-Version: 2.4
Name: algo-visualizer
Version: 0.0.2
Summary: Python API for algo-visualizer.
Project-URL: Homepage, https://github.com/algo-visualizer/pyapi
Project-URL: Repository, https://github.com/algo-visualizer/pyapi.git
Project-URL: Issues, https://github.com/algo-visualizer/pyapi/issues
Project-URL: Documentation, https://algo-visualizer.github.io/pyapi/main/visual.html
Author-email: sweetbrulee <sparrowking002@gmail.com>
License: MIT License
License-File: LICENSE
Keywords: algorithm,visual,visualize
Requires-Python: ==3.13.*
Requires-Dist: pydantic
